jupyterlab_pullrequests/__init__.py
jupyterlab_pullrequests/_version.py
jupyterlab_pullrequests/base.py
jupyterlab_pullrequests/handlers.py
jupyterlab_pullrequests/log.py
jupyterlab_pullrequests/labextension/package.json
jupyterlab_pullrequests/labextension/static/216.df250ba291225fb6b196.js
jupyterlab_pullrequests/labextension/static/317.65e128f796fb51b9706e.js
jupyterlab_pullrequests/labextension/static/534.4edb324bb27cb7d8c6c0.js
jupyterlab_pullrequests/labextension/static/618.e54c5627f383c0311000.js
jupyterlab_pullrequests/labextension/static/697.0dc58cbb71cf8727e6b1.js
jupyterlab_pullrequests/labextension/static/700.3e7bfd536941b3578fd9.js
jupyterlab_pullrequests/labextension/static/762.f7530ae90ac9771960fb.js
jupyterlab_pullrequests/labextension/static/762.f7530ae90ac9771960fb.js.LICENSE.txt
jupyterlab_pullrequests/labextension/static/remoteEntry.c1b855bf3081cc130afb.js
jupyterlab_pullrequests/labextension/static/style.js
jupyterlab_pullrequests/managers/__init__.py
jupyterlab_pullrequests/managers/github.py
jupyterlab_pullrequests/managers/gitlab.py
jupyterlab_pullrequests/managers/manager.py
jupyterlab_pullrequests/tests/__init__.py
jupyterlab_pullrequests/tests/conftest.py
jupyterlab_pullrequests/tests/test_extensions.py
jupyterlab_pullrequests/tests/test_github.py
jupyterlab_pullrequests/tests/test_gitlab.py
jupyterlab_pullrequests/tests/test_handlers_integration.py
jupyterlab_pullrequests/tests/test_manager.py
jupyterlab_pullrequests/tests/sample_responses/github/github_comments_get.json
jupyterlab_pullrequests/tests/sample_responses/github/github_comments_post.json
jupyterlab_pullrequests/tests/sample_responses/github/github_current_user.json
jupyterlab_pullrequests/tests/sample_responses/github/github_list_files.json
jupyterlab_pullrequests/tests/sample_responses/github/github_list_prs.json
jupyterlab_pullrequests/tests/sample_responses/github/github_pr_links.json
jupyterlab_pullrequests/tests/sample_responses/gitlab/get_file.json
jupyterlab_pullrequests-3.0.2.dist-info/LICENSE
jupyterlab_pullrequests-3.0.2.dist-info/METADATA
jupyterlab_pullrequests-3.0.2.dist-info/WHEEL
jupyterlab_pullrequests-3.0.2.dist-info/entry_points.txt
jupyterlab_pullrequests-3.0.2.dist-info/top_level.txt
jupyterlab_pullrequests-3.0.2.dist-info/RECORD
