Metadata-Version: 2.1
Name: jupyterlab-pullrequests
Version: 3.0.2
Summary: Pull Requests for JupyterLab
Home-page: https://github.com/jupyterlab/pull-requests
Author: Jupyter Development Team
License: BSD-3-Clause
Project-URL: Bug Tracker, https://github.com/jupyterlab/pull-requests/issues
Project-URL: CI, https://github.com/jupyterlab/pull-requests/actions
Project-URL: Releases, https://github.com/jupyterlab/pull-requests/releases
Project-URL: Source Code, https://github.com/jupyterlab/pull-requests
Keywords: Interactive,Jupyter,JupyterLab,Notebook,Web,Git,Version Control,Pull Requests
Platform: Linux
Platform: Mac OS X
Platform: Windows
Classifier: Framework :: Jupyter
Classifier: Intended Audience :: Developers
Classifier: Intended Audience :: Information Technology
Classifier: License :: OSI Approved :: BSD License
Classifier: Programming Language :: Python
Classifier: Programming Language :: Python :: 3.6
Classifier: Programming Language :: Python :: 3.7
Classifier: Programming Language :: Python :: 3.8
Classifier: Programming Language :: Python :: 3.9
Classifier: Programming Language :: Python :: 3 :: Only
Classifier: Framework :: Jupyter
Classifier: Framework :: Jupyter :: JupyterLab
Classifier: Framework :: Jupyter :: JupyterLab :: 3
Classifier: Framework :: Jupyter :: JupyterLab :: Extensions
Classifier: Framework :: Jupyter :: JupyterLab :: Extensions :: Prebuilt
Requires-Python: >=3.6
License-File: LICENSE
Requires-Dist: entrypoints (>=0.2.2)
Requires-Dist: jupyterlab (~=3.0)
Requires-Dist: jupyterlab-git (<0.40.0a0,>=0.30.0)
Provides-Extra: coverage
Requires-Dist: diff-match-patch ; extra == 'coverage'
Requires-Dist: flaky ; extra == 'coverage'
Requires-Dist: mock (>=4.0.0) ; extra == 'coverage'
Requires-Dist: pytest ; extra == 'coverage'
Requires-Dist: pytest-asyncio ; extra == 'coverage'
Requires-Dist: pytest-tornasync ; extra == 'coverage'
Requires-Dist: codecov ; extra == 'coverage'
Requires-Dist: pytest-cov ; extra == 'coverage'
Provides-Extra: dev
Requires-Dist: diff-match-patch ; extra == 'dev'
Requires-Dist: flaky ; extra == 'dev'
Requires-Dist: mock (>=4.0.0) ; extra == 'dev'
Requires-Dist: pytest ; extra == 'dev'
Requires-Dist: pytest-asyncio ; extra == 'dev'
Requires-Dist: pytest-tornasync ; extra == 'dev'
Requires-Dist: codecov ; extra == 'dev'
Requires-Dist: pytest-cov ; extra == 'dev'
Requires-Dist: twine ; extra == 'dev'
Provides-Extra: gitlab
Requires-Dist: diff-match-patch ; extra == 'gitlab'
Provides-Extra: test
Requires-Dist: diff-match-patch ; extra == 'test'
Requires-Dist: flaky ; extra == 'test'
Requires-Dist: mock (>=4.0.0) ; extra == 'test'
Requires-Dist: pytest ; extra == 'test'
Requires-Dist: pytest-asyncio ; extra == 'test'
Requires-Dist: pytest-tornasync ; extra == 'test'
